setup.py
piforge/__init__.py
piforge/__main__.py
piforge/minecraftstuff.py
piforge/minecraftturtle.py
piforge/servo.py
piforge/servotest.py
piforge/setupAuto.sh
piforge.egg-info/PKG-INFO
piforge.egg-info/SOURCES.txt
piforge.egg-info/dependency_links.txt
piforge.egg-info/entry_points.txt
piforge.egg-info/not-zip-safe
piforge.egg-info/requires.txt
piforge.egg-info/top_level.txt