Metadata-Version: 1.0
Name: piforge
Version: 1.4.3
Summary: iforge for rPi server component
Home-page: https://github.com/shawt/piforge
Author: Trevor Shaw
Author-email: shawt@genlrn.com
License: MIT
Platform: UNKNOWN
